met4dream/__init__.py
met4dream/metocean.py
met4dream/spatial.py
met4dream-1.5.dist-info/DESCRIPTION.rst
met4dream-1.5.dist-info/METADATA
met4dream-1.5.dist-info/RECORD
met4dream-1.5.dist-info/WHEEL
met4dream-1.5.dist-info/metadata.json
met4dream-1.5.dist-info/top_level.txt
