Metadata-Version: 2.0
Name: met4dream
Version: 1.5
Summary: ROMS-Norkyst800m Metocean Data Extraction and Analysis
Home-page: UNKNOWN
Author: Oivin Aarnes
Author-email: oivin.aarnes@dnvgl.com
License: MIT
Keywords: SeaFAN metocean data adaptation for DREAM modelling
Platform: Windows
Classifier: Development Status :: 5 - Production/Stable
Classifier: Intended Audience :: Developers
Classifier: Topic :: Scientific/Engineering :: GIS
Classifier: Programming Language :: Python :: 2.7
Classifier: Programming Language :: Python :: 3
Classifier: Programming Language :: Python :: 3.2
Classifier: Programming Language :: Python :: 3.3
Classifier: Programming Language :: Python :: 3.4
Classifier: Programming Language :: Python :: 3.5
Requires-Dist: nco
Requires-Dist: netCDF4
Requires-Dist: numpy
Requires-Dist: requests
